{
  "source": "https://frequentmiler.com/current-point-transfer-bonuses/",
  "lastUpdated": "2026-07-13T15:51:12+00:00",
  "count": 7,
  "bonuses": [
    {
      "from": "Chase Ultimate Rewards",
      "details": "30% transfer bonus from Chase Ultimate Rewards to Virgin Atlantic Flying Club",
      "pct": "30%",
      "url": "https://frequentmiler.com/chase-ultimate-rewards-virgin-atlantic-30-percent-transfer-bonus/",
      "start": "06/09/26",
      "end": "07/14/26"
    },
    {
      "from": "Amex Membership Rewards",
      "details": "20% transfer bonus from Amex Membership Rewards to Hilton",
      "pct": "20%",
      "url": "https://frequentmiler.com/20-percent-transfer-bonus-american-express-membership-rewards-hilton-honors/",
      "start": "07/01/26",
      "end": "07/14/26"
    },
    {
      "from": "Amex Membership Rewards",
      "details": "15% transfer bonus from Amex Membership Rewards to Avianca LifeMiles",
      "pct": "15%",
      "url": "https://frequentmiler.com/15-transfer-bonus-from-amex-membership-rewards-to-avianca-lifemiles/",
      "start": "06/15/26",
      "end": "07/15/26"
    },
    {
      "from": "Citi ThankYou Rewards",
      "details": "50% transfer bonus from Citi ThankYou Rewards to ALL Accor",
      "pct": "50%",
      "url": "https://frequentmiler.com/50-percent-transfer-bonus-citi-thankyou-accor-all/",
      "start": "06/14/26",
      "end": "07/18/26"
    },
    {
      "from": "Rove Miles",
      "details": "25% transfer bonus from Rove Miles to Frontier Miles",
      "pct": "25%",
      "url": "https://frequentmiler.com/frontier-added-as-a-rove-transfer-partner-get-25-transfer-bonus-through-7-31-26/",
      "start": "07/01/26",
      "end": "07/31/26"
    },
    {
      "from": "Capital One Miles",
      "details": "30% transfer bonus from Capital One Miles to EVA Air Infinity MileageLands",
      "pct": "30%",
      "url": "https://frequentmiler.com/30-transfer-bonus-capital-one-miles-eva-air/",
      "start": "07/01/26",
      "end": "07/31/26"
    },
    {
      "from": "Amex Membership Rewards",
      "details": "30% transfer bonus from Amex Membership Rewards to Virgin Atlantic Flying Club",
      "pct": "30%",
      "url": "https://frequentmiler.com/30-percent-transfer-bonus-american-express-membership-rewards-virgin-atlantic/",
      "start": "07/01/26",
      "end": "07/31/26"
    }
  ]
}